textgame/__init__.py
textgame/lib.py
textgame/object.py
textgame_gma-0.2.dist-info/METADATA
textgame_gma-0.2.dist-info/WHEEL
textgame_gma-0.2.dist-info/top_level.txt
textgame_gma-0.2.dist-info/RECORD
