Metadata-Version: 2.1
Name: textgame-gma
Version: 0.2
Summary: A library for creating text-based games.
Home-page: https://github.com/bruno1994122/textgame
Author: peg
Author-email: jpg01153@gmail.com
Classifier: Programming Language :: Python :: 3
Classifier: License :: OSI Approved :: MIT License
Classifier: Operating System :: OS Independent
Requires-Python: >=3.6
